{
    "type": "FeatureCollection",
    "features": [
        {
            "type": "Feature",
            "properties": {},
            "geometry": {
                "type": "LineString",
                "coordinates": [
                    [
                        114.98291015625,
                        41.599013054830216
                    ],
                    [
                        113.85406494140624,
                        41.50652046891492
                    ],
                    [
                        113.85406494140624,
                        39.743098286948275
                    ],
                    [
                        119.03961181640624,
                        39.734650174341866
                    ],
                    [
                        119.190673828125,
                        42.14915080911929
                    ],
                    [
                        115.00762939453125,
                        41.623655390686395
                    ],
                    [
                        114.99114990234375,
                        41.6195489884308
                    ]
                ]
            }
        }
    ]
}